Workbook

Sheet Agreement
A3: Category | B3: Count (Ryan) | C3: Count (Randy) | D3: Agreed
A4: Bank account or service | B4: =COUNTIF(Labels_150!$C$2:$C$151,A4) -> 23 | C4: =COUNTIF(Labels_150!$D$2:$D$151,A4) -> 29 | D4: =COUNTIFS(Labels_150!$C$2:$C$151,A4,Labels_150!$D$2:$D$151,A4) -> 22
A5: Credit card | B5: =COUNTIF(Labels_150!$C$2:$C$151,A5) -> 18 | C5: =COUNTIF(Labels_150!$D$2:$D$151,A5) -> 16 | D5: =COUNTIFS(Labels_150!$C$2:$C$151,A5,Labels_150!$D$2:$D$151,A5) -> 16
A6: Consumer loan | B6: =COUNTIF(Labels_150!$C$2:$C$151,A6) -> 21 | C6: =COUNTIF(Labels_150!$D$2:$D$151,A6) -> 19 | D6: =COUNTIFS(Labels_150!$C$2:$C$151,A6,Labels_150!$D$2:$D$151,A6) -> 18
A7: Mortgage | B7: =COUNTIF(Labels_150!$C$2:$C$151,A7) -> 20 | C7: =COUNTIF(Labels_150!$D$2:$D$151,A7) -> 20 | D7: =COUNTIFS(Labels_150!$C$2:$C$151,A7,Labels_150!$D$2:$D$151,A7) -> 19
A8: Credit reporting | B8: =COUNTIF(Labels_150!$C$2:$C$151,A8) -> 27 | C8: =COUNTIF(Labels_150!$D$2:$D$151,A8) -> 29 | D8: =COUNTIFS(Labels_150!$C$2:$C$151,A8,Labels_150!$D$2:$D$151,A8) -> 25
A9: Debt collection | B9: =COUNTIF(Labels_150!$C$2:$C$151,A9) -> 21 | C9: =COUNTIF(Labels_150!$D$2:$D$151,A9) -> 21 | D9: =COUNTIFS(Labels_150!$C$2:$C$151,A9,Labels_150!$D$2:$D$151,A9) -> 20
A10: Money transfer or service | B10: =COUNTIF(Labels_150!$C$2:$C$151,A10) -> 20 | C10: =COUNTIF(Labels_150!$D$2:$D$151,A10) -> 14 | D10: =COUNTIFS(Labels_150!$C$2:$C$151,A10,Labels_150!$D$2:$D$151,A10) -> 13
A11: Other / None | B11: =COUNTIF(Labels_150!$C$2:$C$151,A11) -> 0 | C11: =COUNTIF(Labels_150!$D$2:$D$151,A11) -> 2 | D11: =COUNTIFS(Labels_150!$C$2:$C$151,A11,Labels_150!$D$2:$D$151,A11) -> 0
A15: Tickets labelled by both (N) | B15: =COUNTA(Labels_150!$A$2:$A$151) -> 150
A16: Agreements | B16: =SUMPRODUCT((Labels_150!$C$2:$C$151=Labels_150!$D$2:$D$151)*1) -> 133
A17: Disagreements | B17: =B15-B16 -> 17

Sheet Labels_150
A1: ticket_number | B1: narrative | C1: label 1 | D1: label 2 | E1: match | F1: proposed_final_label
A2: 3021 | B2: In XXXX, I was taking XXXX 's level classes using my GI benefits through the Department of Veterans Affairs. Due to multiple XXXX while on XXXX XXXX, I was forced to withdraw from the courses. I was told by XXXX University that I would not be charged any fees due to my extenuating circumstances. Several months passed and I received a packet of undelivered letters from the VA, despite receiving other mail from them in the meantime. This packet said that I had a payment due that was now in collections. After many conversations between the VA and XXXX, a miscommunication was found between those two parties, and everything was supposed to be cleared as of XX/XX/XXXX. I checked my credit report in XX/XX/XXXX and found that there was nearly 18 months of collections on my account, ending in XX/XX/XXXX, for this miscommunication between the VA and XXXX. I wanted to have that removed from my credit report so I submitted a dispute through Experian in XX/XX/XXXX explaining my situation and asking that those months of collections be removed. At the end of XXXX, I received a response that all the months of collections had been removed as I had asked, but now it was showing the account was in collections for only the month of XX/XX/XXXX. This makes absolutely no sense as they previously had the collections ending in XX/XX/XXXX when the issue was resolved. I reached out via phone to address this new issue, and they were not able to assist and suggested I submit a new dispute. I did this in early XX/XX/XXXX. I recently received the results of this second dispute, and it appears that Experian removed the collections flag from XX/XX/XXXX, but now has it in collections for only XX/XX/XXXX. I am unsure what to do at this point as I have reached out via phone and electronic dispute and can not resolve this issue. It has dropped my credit score nearly 30 points in the past two months because of their errors. | C2: Credit reporting | D2: Credit reporting | E2: =IF(C2=D2,"Agree","Disagree") -> Agree | F2: Credit reporting
A3: 3024 | B3: On XXXX XXXX XXXX I attempted to purchase a vehicle from XXXX of XXXX XXXX, and XXXX, XXXX dealership . I remained at the dealership for approximately eight ( 8 ) hours, completed negotiations, and signe3d purchase and finance documents for a XXXX XXXXXXXX XXXX. I was expressly told that Westlake Financial was the lender associated with my transaction. XXXX provided written financing worksheets quoting specific APR 's and payment amounts. XXXX also provided a document titled " Credit Score and the Price You Pay for Credit, '' stating that my XXXX credit score was " not available. '' Despite this, XXXX requested and transmitted my Social Security number, submitted my application to lenders, and represented that financing was proceeding. I was never issued a denial, conditional denial, or adverse action notice. After I had signed documents and waited several hours, XXXX abruptly required me to leave, claiming that the vehicle had been sold to another buyer paying cash. This explanation occurred after lender involvement and document execution. Following this, XXXX refused to provide copies of documents I signed and refused to disclose how my personal and financial information was used or transmitted. This conduct violates federal consumer-credit laws : 1. Failure to provide an adverse action notice - after terminating or refusing to consummate a credit transaction ( ECOA, 15 U.S.C. 1691 ( d ) ). 2. Use of consumer credit information without transparent disclosure and failure to provide post-use disclosure3s ( FCRA, 15 U.S.C. 1681 B, 1681M ) 3. Deceptive and abusive practices, including pretextual explanations to avoid required notices and withholding consumer records ( CFPA, 12 U.S.C. 5531, 5536 ). XXXX and its partners used my credit information, identified a lender, quoted loan terms, and then concealed the credit outcome while retaining my personal data. | C3: Consumer loan | D3: Consumer loan | E3: =IF(C3=D3,"Agree","Disagree") -> Agree | F3: Consumer loan
A4: 3032 | B4: I am writing to dispute an unauthorized bank account listed under my name and Social Security number. According to 15 U.S.C. 1681b of the Fair Credit Reporting Act ( FCRA ), consumer reports may only be accessed for specific permissible purposes and with the consumer 's knowledge or consent. I did not open any bank account associated with Wells Fargo nor did I authorize XXXX XXXX XXXX XXXX XXXX or any affiliated financial institution to access or use my consumer information in connection with this account. This is a serious matter, as it may indicate identity theft or unauthorized use of my personal information.Because this inquiry was made without a permissible purpose as defined under federal law, I am requesting that you immediately remove any unauthorized accounts and related inquiries associated with my name. This is a private communication. I reserve all rights. | C4: Credit reporting | D4: Credit reporting | E4: =IF(C4=D4,"Agree","Disagree") -> Agree | F4: Credit reporting
A5: 3037 | B5: I pay mortgage on XX/XX/XXXX for XXXX for the month of XXXX they said i should have pay XXXX in XXXX if you look at my new Escrow payment it said that my new payment started in XX/XX/XXXX XXXX that because they never deduct XXXX dollar that they took out for Escrow started at XX/XX/XXXX and the new Escrow payment of {$810.00} that I pay off on XX/XX/XXXX they never deduct the {$67.00} from my Escrow my new mortgage payment should be XXXX not XXXX they are only making me late on my mortgage because of this | C5: Mortgage | D5: Mortgage | E5: =IF(C5=D5,"Agree","Disagree") -> Agree | F5: Mortgage
A6: 3039 | B6: REFERENCE # XXXX I was a victim of identity theft six-seven years ago the accounting question with XXXX was discovered to be fraudulent never used by me did not belong to me yes the information was similar that's why it's called identity theft XXXX recognize this they closed the account it was never reported to any of the major credit bureaus once it was discovered what it happened police reports were filed multiple letters were sent back and forth and everything was eventually resolved until about a month ago when I received the first letter from this company stating I owed them a debt I immediately sent a letter explaining what I just explained I told them unless they had some proof which I knew they wouldn't to stop all further Communications with me that I had no intentions on paying them any money they sent me another letter helping this was their proof it's just some printing information there's absolutely nothing here that we didn't already know it shows XXXX shows an account number show the balance well yes nobody 's disputing that the account was opened it just wasn't open by me and Everyone except for this company seems to understand that I don't feel they're taking this matter seriously but when you start reporting it to the credit bureaus and you start affecting my credit score it becomes a serious issue | C6: Debt collection | D6: Debt collection | E6: =IF(C6=D6,"Agree","Disagree") -> Agree | F6: Debt collection
A7: 3049 | B7: Discover Bank initiated and authorized a {$21000.00} fraudulent wire transfer with no attempt to contact or approve the transfer with myself or my husband who is a joint owner. We did nothing to initiate this transfer and only learned of it after logging in to our bank account. Someone was able to hack in to our account and change our personal information. We received no notification of suspicious activity and no recourse from Discover at all. | C7: Money transfer or service | D7: Bank account or service | E7: =IF(C7=D7,"Agree","Disagree") -> Disagree | F7: Money transfer or service
A8: 3069 | B8: In XXXX or XXXX of 2015 Macy 's changed their credit card from a XXXX to an XXXX card. At the time, we had the XXXX card set up on our Bill Pay system. As our use of this card is occasional and only used at Macy 's, we depended on the Bill Pay process and paid when notified a bill was due. When the account changed to XXXX, apparently the bill pay information did not transfer. This would have been OK, assuming that they notified us via email or with a paper statement that an amount was due. Last night, our card was declined at Macy 's and we were informed that we were overdue and owed {$480.00} dollars, including late fees and finance charges of {$120.00}! When we called, we were offered a relief of {$38.00} dollars, which we declined and disputed the fee. When asked how the billing statement was delivered, the agent said via email. When asked what email was used, the agent could not cite the email. Effectively, we were not billed or notified that we were behind payments in any way. If we had not attempted to use the card, the charges would have continued to accrue. We immediately paid the amount due, but their is no way to dispute the late fees and finance charges. It appears to us that the transfer of data and other information during the transition from XXXX to XXXX was improperly handled. | C8: Credit card | D8: Credit card | E8: =IF(C8=D8,"Agree","Disagree") -> Agree | F8: Credit card
A9: 3134 | B9: I was making a withdrawal from the ATM machine at Cadence Bank on XX/XX/2024. While still conducting my transaction ; I was startled after looking in my rear view mirror. I saw man just standing and staring at my vehicle from behind and the bank was open for operating hours.I had my car door cracked open and paused mid ways of my transaction to shut and lock my door before completing my transaction. Intially I had my car door cracked open so I could reach the ATM machines buttons and retrieve my cash. I was afraid that I wasn't sure if I should call thr poloce or pull off without my card. I closed and locked my doors and and turned on my rear view camera and took a photo. It was then that I recognized the man was wearing a Cadence 's employee lime green XXXX shirt. I then proceeded and completed my withdrawal but I was confused as to why he stayed behind me the entire time. Why I was pulling off the lot and waiting for on coming traffic to cease so I could turn. I looked in my rear veiw mirror out of curiosity of his odd behavior. The employee walked up for 3 seconds or less and looked at the ATM. Then he swiftly looked in my direction then went back into Cadence 's Bank. I felt so embarrassed to have the Bank 's branch manager intrusively surveillance me alone and no other vehicles that came through the bank 's drive thru. It was after this inappropriate encounter that I learned ; that this employee named XXXX XXXX is the branch manager of the bank. I have photographic evidence it needed | C9: Bank account or service | D9: Bank account or service | E9: =IF(C9=D9,"Agree","Disagree") -> Agree | F9: Bank account or service
A10: 3145 | B10: Subject : Deceptive Marketing and Failure to Honor Promotional Bonus via Partner XXXXXXXX Description of Complaint : I am filing this complaint regarding SoFi 's failure to honor a new account promotional offer marketed through their affiliate partner, XXXX. 1. The Inducement : I was induced to open a new Checking & Savings account with SoFi based on a specific advertisement on the XXXX platform. The offer promised a cash bonus of XXXX upon opening a new account and receiving a qualifying direct deposit. This promotional offer was the primary reason I chose to do business with SoFi. 2. My Compliance : Acting in good faith, I fulfilled all requirements outlined in the promotion : I initiated the account application via the designated affiliate link on XXXX XXXX My account was successfully opened on XXXX XXXX I completed a qualifying Direct Deposit on XXXX XXXX, which posted to my account as required. 3. The Violation : Despite meeting all terms, the promised bonus has not been paid. XXXX has denied the payout saying Sofi fails to report a transaction to XXXX or fails to make payment to XXXX for any reason. Since SoFi utilizes XXXX as a marketing channel to acquire new customers, SoFi bears the ultimate responsibility for ensuring its marketing partners honor their advertised offers. 4. Impact : I have wasted significant time attempting to resolve this with customer support to no avail. The failure to provide the advertised incentive constitutes a " Unfair, Deceptive, or Abusive Act or Practice '' ( UDAAP ), as the financial product was marketed with a benefit that was not delivered. | C10: Bank account or service | D10: Bank account or service | E10: =IF(C10=D10,"Agree","Disagree") -> Agree | F10: Bank account or service
A11: 3147 | B11: Hello, I received a scam call yesterday from XXXX. The caller claimed to be from Discover, stating there were suspicious purchases on my credit card. They were extremely convincing and had access to personal details such as my birthdate, address, and age. Although I became suspicious and questioned them, they continued to assure me it was legitimate. They even sent a text message for " verification '' from short code XXXX. Unfortunately, I did share the last XXXX digits of my Social Security number before fully realizing it was a scam. As a precaution, I have canceled my Discover card and requested a new one. I've also blocked both the phone number and short code and reported the incident to XXXX I have started a subscription with XXXX Please let me know if there are any additional steps I should take to protect my identity or account. Thank you, XXXX | C11: Credit card | D11: Credit card | E11: =IF(C11=D11,"Agree","Disagree") -> Agree | F11: Credit card
A12: 3150 | B12: XXXX XXXXXXXX XXXX XXXX and Bank of America credit card pulled my credit on all 3 bureaus. XXXX, XXXX, XXXX. This happened over night at XXXX and XXXX. I did not request any credit to be pulled nor did I inquire about getting a credit card. I currently do not have any open credit cards with these companies | C12: Credit reporting | D12: Credit reporting | E12: =IF(C12=D12,"Agree","Disagree") -> Agree | F12: Credit reporting
A13: 3155 | B13: I have disputed collection information reported by XXXX XXXX on behalf of XXXX. I have disputed the collection account XXXX with XXXX, XXXX, and Experian. I do not believe the investigation is properly being executed. It seems like the credit bureaus are working for the collection agency and agree with the electronic response received from XXXX XXXX on behalf of XXXX. The account remained on my credit report, but I do not have a reason why the account remain when XXXX shows I do not owe them and the balance was resolved. Transunion die not report XXXX XXXX on my credit report in XX/XX/XXXX, but soon as I disputed the item it was added to my credit report in XX/XX/XXXX and the investigation with XXXX XXXX has not been resolved. | C13: Credit reporting | D13: Credit reporting | E13: =IF(C13=D13,"Agree","Disagree") -> Agree | F13: Credit reporting
... A151: 3998 | B151: I have opened a money market account and a realtionship checking account with them and the promotion code is XXXX XXXX- Promotion, XX/XX/XXXX, XXXX {$300.00}. where they agree to give me XXXX bonus as long as I put XXXX in their account and leave for 90 days. I follow their request and they refuse to give me bonus, claim that I need flyers to have that. However, it was a public offer that post online, and I have confirmed with banker for this as well, they keep that offer online even I tried to resolve the problem with them till XX/XX/XXXX. I am frustrated the bank service can't promise what they have to me. Go to the website, even now it is clear they still run this promo period to period. The requirement is exact the same. They just cheat with customer and tried to get our money, I am disappointed about commerce bank credit -- could not keep the word as they said on flyer. https : //www.commercebank.com/XXXX | C151: Bank account or service | D151: Bank account or service | E151: =IF(C151=D151,"Agree","Disagree") -> Agree | F151: Bank account or service
